setup.py
robograph/__init__.py
robograph.egg-info/PKG-INFO
robograph.egg-info/SOURCES.txt
robograph.egg-info/dependency_links.txt
robograph.egg-info/requires.txt
robograph.egg-info/top_level.txt
robograph/datamodel/__init__.py
robograph/datamodel/base/__init__.py
robograph/datamodel/base/exceptions.py
robograph/datamodel/base/graph.py
robograph/datamodel/base/node.py
robograph/datamodel/nodes/__init__.py
robograph/datamodel/nodes/plotter.py
robograph/datamodel/nodes/serializer.py
robograph/datamodel/nodes/lib/__init__.py
robograph/datamodel/nodes/lib/apply.py
robograph/datamodel/nodes/lib/branching.py
robograph/datamodel/nodes/lib/buffers.py
robograph/datamodel/nodes/lib/clock.py
robograph/datamodel/nodes/lib/email.py
robograph/datamodel/nodes/lib/files.py
robograph/datamodel/nodes/lib/functional_operators.py
robograph/datamodel/nodes/lib/http.py
robograph/datamodel/nodes/lib/logics.py
robograph/datamodel/nodes/lib/maths.py
robograph/datamodel/nodes/lib/printer.py
robograph/datamodel/nodes/lib/randoms.py
robograph/datamodel/nodes/lib/strings.py
robograph/datamodel/nodes/lib/transcoders.py
robograph/datamodel/nodes/lib/value.py
robograph/datamodel/tests/__init__.py
robograph/datamodel/tests/test_apply.py
robograph/datamodel/tests/test_buffers.py
robograph/datamodel/tests/test_clock.py
robograph/datamodel/tests/test_console_printer.py
robograph/datamodel/tests/test_functional_operators.py
robograph/datamodel/tests/test_graph.py
robograph/datamodel/tests/test_http.py
robograph/datamodel/tests/test_ifthenapply.py
robograph/datamodel/tests/test_ifthenreturn.py
robograph/datamodel/tests/test_log_printer.py
robograph/datamodel/tests/test_logics.py
robograph/datamodel/tests/test_maths.py
robograph/datamodel/tests/test_serializer.py
robograph/datamodel/tests/test_strings.py
robograph/datamodel/tests/test_text_file_reader.py
robograph/datamodel/tests/test_text_file_writer.py
robograph/datamodel/tests/test_tocsv.py
robograph/datamodel/tests/test_tojson.py
robograph/datamodel/tests/test_value.py
sample_graphs/delayed_sum_and_product.py
sample_graphs/drawing.py
sample_graphs/email_geolocated_ip.py
sample_graphs/http_fun.py
