Metadata-Version: 1.1
Name: robograph
Version: 0.0.3
Summary: A graph-oriented algorithmic engine
Home-page: http://github.com/csparpa/robograph
Author: Claudio Sparpaglione (@csparpa)
Author-email: csparpa@gmail.com
License: MIT
Keywords: robograph graph node engine computing
Platform: UNKNOWN
Classifier: License :: OSI Approved :: MIT License
Classifier: Programming Language :: Python
Classifier: Natural Language :: English
Classifier: Operating System :: OS Independent
Classifier: Development Status :: 4 - Beta
Classifier: Intended Audience :: Developers
Classifier: Topic :: Software Development :: Libraries
